listener/__init__.py
listener/admin.py
listener/apps.py
listener/models.py
listener/processor.py
listener/settings.py
listener/tests.py
listener/urls.py
listener/utils.py
listener/views.py
listener/migrations/0001_initial.py
listener/migrations/__init__.py
django_listener-0.1.dist-info/LICENSE
django_listener-0.1.dist-info/METADATA
django_listener-0.1.dist-info/WHEEL
django_listener-0.1.dist-info/top_level.txt
django_listener-0.1.dist-info/RECORD
