Metadata-Version: 2.1
Name: django-listener
Version: 0.1
Summary: Automatically listens and processes webhooks from third party services
Home-page: https://github.com/sirrobot01/django-listener
Author: Mukhtar Akere
Author-email: akeremukhtar10@gmail.com
License: BSD-3-Clause
Project-URL: Source, https://github.com/sirrobot01/django-listener
Platform: UNKNOWN
Classifier: Environment :: Web Environment
Classifier: Framework :: Django
Classifier: Intended Audience :: Developers
Classifier: License :: OSI Approved :: MIT License
Classifier: Operating System :: OS Independent
Classifier: Programming Language :: Python
Classifier: Topic :: Internet :: WWW/HTTP
Classifier: Topic :: Internet :: WWW/HTTP :: Dynamic Content
License-File: LICENSE
Requires-Dist: django (>=2.2)
